wtf_plus/__init__.py
wtf_plus/plus.py
wtf_plus-0.2.2.dist-info/METADATA
wtf_plus-0.2.2.dist-info/WHEEL
wtf_plus-0.2.2.dist-info/entry_points.txt
wtf_plus-0.2.2.dist-info/top_level.txt
wtf_plus-0.2.2.dist-info/RECORD
