Metadata-Version: 2.1
Name: wtf_plus
Version: 0.2.2
Summary: Default template for PDM package
Author-email: thephunkmonk <andrewchoi1218@gmail.com>
License: MIT
Requires-Python: >=3.9
